imgora/__init__.py
imgora/_converter.py
imgora/_core.py
imgora/_imagor.py
imgora/_thumbor.py
imgora/_wsrv_nl.py
imgora/decorator.py
imgora/py.typed
imgora-0.0.1.dist-info/METADATA
imgora-0.0.1.dist-info/WHEEL
imgora-0.0.1.dist-info/licenses/LICENSE
imgora-0.0.1.dist-info/RECORD
