Metadata-Version: 2.4
Name: imgora
Version: 0.0.1
Summary: Chainable image URL generator for Imagor, Thumbor and Wsrv.nl with full filter support
Project-URL: Repository, https://github.com/burgdev/imgora
Project-URL: Documentation, https://burgdev.github.io/imgora/
Project-URL: Changelog, https://github.com/burgdev/imgora/blob/main/CHANGELOG.md
Project-URL: Releases, https://github.com/burgdev/imgora/releases
License: MIT
License-File: LICENSE
Classifier: Development Status :: 4 - Beta
Classifier: Intended Audience :: Developers
Classifier: License :: OSI Approved :: MIT License
Classifier: Programming Language :: Python :: 3.11
Classifier: Programming Language :: Python :: 3.12
Classifier: Topic :: Multimedia :: Graphics :: Graphics Conversion
Classifier: Topic :: Software Development :: Libraries :: Python Modules
Requires-Python: >=3.11
Requires-Dist: requests>=2.28.0
